{"cameraMode":{"drawMode":0,"name":"Shaded","section":"Shading Mode"},"sceneLighting":true,"audioPlay":false,"sceneViewState":{"showFog":true,"showMaterialUpdate":false,"showSkybox":true,"showFlares":true,"showImageEffects":true,"showParticleSystems":true},"in2DMode":false,"pivot":{"x":-6.429286956787109,"y":-6.73810338973999,"z":15.28283977508545},"rotation":{"x":-0.1978677362203598,"y":0.07724714279174805,"z":-0.015643790364265443,"w":-0.977055013179779},"size":26.56728172302246,"orthographic":false}